{
  "auth_user": "david",
  "auth_password": "password",
  "host_port": "192.168.15.103(1414),192.168.15.103(1415)",
  "queue_manager": "QM1",
  "group": "Centos MQs",
  "debug": "true",
  "channel": ".*",
  "server_connection": "QM1.CHANNEL",
  "listener": ".*",
  "key_repo_location": "",
  "exclude_system": "",
  "reset_q_stats": "",
  "queues": "QUEUE1,QUEUE2,*,QUEUE3,Q*,QUEUE0,QUEUE1,QUEUE2,QUEUE3,QUEUE4,QUEUE5,QUEUE6,QUEUE7,QUEUE8,QUEUE9,QUEUE10,QUEUE11,QUEUE12,QUEUE13,QUEUE14,QUEUE15,QUEUE16,QUEUE17,QUEUE18,QUEUE19,QUEUE20,QUEUE21,QUEUE22,QUEUE23,QUEUE24,QUEUE25,QUEUE26,QUEUE27,QUEUE28,QUEUE29,QUEUE30,QUEUE31,QUEUE32,QUEUE33,QUEUE34,QUEUE35,QUEUE36,QUEUE37,QUEUE38,QUEUE39,QUEUE40,QUEUE41,QUEUE42,QUEUE43,QUEUE44,QUEUE45,QUEUE46,QUEUE47,QUEUE48,QUEUE49,QUEUE50,QUEUE51,QUEUE52,QUEUE53,QUEUE54,QUEUE55,QUEUE56,QUEUE57,QUEUE58,QUEUE59,QUEUE60,QUEUE61,QUEUE62,QUEUE63,QUEUE64,QUEUE65,QUEUE66,QUEUE67,QUEUE68,QUEUE69,QUEUE70,QUEUE71,QUEUE72,QUEUE73,QUEUE74,QUEUE75,QUEUE76,QUEUE77,QUEUE78,QUEUE79,QUEUE80,QUEUE81,QUEUE82,QUEUE83,QUEUE84,QUEUE85,QUEUE86,QUEUE87,QUEUE88,QUEUE89,QUEUE90,QUEUE91,QUEUE92,QUEUE93,QUEUE94,QUEUE95,QUEUE96,QUEUE97,QUEUE98,QUEUE99,QUEUE100,QUEUE101,QUEUE102,QUEUE103,QUEUE104,QUEUE105,QUEUE106,QUEUE107,QUEUE108,QUEUE109,QUEUE110,QUEUE111,QUEUE112,QUEUE113,QUEUE114,QUEUE115,QUEUE116,QUEUE117,QUEUE118,QUEUE119,QUEUE120,QUEUE121,QUEUE122,QUEUE123,QUEUE124,QUEUE125,QUEUE126,QUEUE127,QUEUE128,QUEUE129,QUEUE130,QUEUE131,QUEUE132,QUEUE133,QUEUE134,QUEUE135,QUEUE136,QUEUE137,QUEUE138,QUEUE139,QUEUE140,QUEUE141,QUEUE142,QUEUE143,QUEUE144,QUEUE145,QUEUE146,QUEUE147,QUEUE148,QUEUE149",
  "cipher_spec": ""

}